image_api/__init__.py
image_api/_base.py
image_api/_image_api.py
image_api/_image_item.py
image_api/config.py
image_api-0.1.1.dist-info/METADATA
image_api-0.1.1.dist-info/WHEEL
image_api-0.1.1.dist-info/top_level.txt
image_api-0.1.1.dist-info/RECORD
